lancalc/__init__.py
lancalc/__main__.py
lancalc/adapters.py
lancalc/cli.py
lancalc/core.py
lancalc/gui.py
lancalc/main.py
lancalc-0.1.11.dist-info/licenses/LICENSE
lancalc-0.1.11.dist-info/METADATA
lancalc-0.1.11.dist-info/WHEEL
lancalc-0.1.11.dist-info/entry_points.txt
lancalc-0.1.11.dist-info/top_level.txt
lancalc-0.1.11.dist-info/RECORD
