Metadata-Version: 2.4
Name: lancalc
Version: 0.1.11
Summary: A desktop application for calculating network configurations
Author-email: Aleksandr Pimenov <wachawo@gmail.com>
Maintainer-email: Aleksandr Pimenov <wachawo@gmail.com>
License: MIT License
Project-URL: Homepage, https://github.com/wachawo/lancalc
Project-URL: Repository, https://github.com/wachawo/lancalc
Project-URL: Documentation, https://github.com/wachawo/lancalc#readme
Project-URL: Bug Reports, https://github.com/wachawo/lancalc/issues
Keywords: network,calculator,subnet,ip,address
Classifier: Development Status :: 4 - Beta
Classifier: Intended Audience :: System Administrators
Classifier: Intended Audience :: Information Technology
Classifier: Operating System :: OS Independent
Classifier: Programming Language :: Python :: 3
Classifier: Programming Language :: Python :: 3.9
Classifier: Programming Language :: Python :: 3.10
Classifier: Programming Language :: Python :: 3.11
Classifier: Programming Language :: Python :: 3.12
Classifier: Programming Language :: Python :: 3 :: Only
Classifier: License :: OSI Approved :: MIT License
Classifier: Topic :: System :: Networking
Classifier: Topic :: Utilities
Requires-Python: >=3.9
License-File: LICENSE
Requires-Dist: netifaces>=0.11.0; platform_system == "Linux"
Requires-Dist: PyQt5>=5.15
Provides-Extra: dev
Requires-Dist: pytest>=8.0.0; extra == "dev"
Requires-Dist: pytest-qt>=4.0.0; extra == "dev"
Requires-Dist: pre-commit; extra == "dev"
Requires-Dist: flake8; extra == "dev"
Provides-Extra: dist
Requires-Dist: PyInstaller>=6.0.0; extra == "dist"
Provides-Extra: nogui
Requires-Dist: netifaces>=0.11.0; platform_system == "Linux" and extra == "nogui"
Dynamic: license-file
